psutil_extra/__init__.py
psutil_extra/_bsd.py
psutil_extra/_cache.py
psutil_extra/_ffi.py
psutil_extra/_psdragonfly.py
psutil_extra/_psfreebsd.py
psutil_extra/_pslinux.py
psutil_extra/_psmacosx.py
psutil_extra/_psnetbsd.py
psutil_extra/_psopenbsd.py
psutil_extra/_psposix.py
psutil_extra/_pssolaris.py
psutil_extra/_util.py
tests/__init__.py
tests/test_as_dict.py
tests/test_main.py
tests/test_resource.py
tests/test_signal.py
tests/util.py
psutil_extra-0.2.0.dist-info/LICENSE
psutil_extra-0.2.0.dist-info/METADATA
psutil_extra-0.2.0.dist-info/WHEEL
psutil_extra-0.2.0.dist-info/top_level.txt
psutil_extra-0.2.0.dist-info/RECORD
