Metadata-Version: 2.1
Name: psutil-extra
Version: 0.2.0
Summary: Some helper functions to go along with the ones in psutil
Home-page: https://github.com/cptpcrd/psutil-extra
License: MIT
Project-URL: Documentation, https://psutil-extra.readthedocs.io/en/latest
Keywords: psutil
Platform: UNKNOWN
Classifier: License :: OSI Approved :: MIT License
Classifier: Programming Language :: Python :: 3.7
Classifier: Programming Language :: Python :: 3.8
Classifier: Operating System :: POSIX :: Linux
Classifier: Operating System :: POSIX :: BSD :: NetBSD
Classifier: Operating System :: POSIX :: BSD :: FreeBSD
Classifier: Operating System :: POSIX :: SunOS/Solaris
Classifier: Operating System :: MacOS :: MacOS X
Requires-Python: >=3.7
Requires-Dist: psutil
